tensorsequence/__init__.py
tensorsequence/tensorsequence.py
tensorsequence/tests/__init__.py
tensorsequence/tests/test_tensorsequence.py
tensorsequence-0.3.0.dist-info/METADATA
tensorsequence-0.3.0.dist-info/WHEEL
tensorsequence-0.3.0.dist-info/top_level.txt
tensorsequence-0.3.0.dist-info/RECORD
