Metadata-Version: 2.1
Name: tensorsequence
Version: 0.3.0
Summary: manipulate sequences of tensors
Home-page: https://github.com/theAdamColton/tensorsequence
Author: Adam Colton
Requires-Dist: torch >=2.0.1
